chaquopy_stubgen/__init__.py
chaquopy_stubgen/__main__.py
chaquopy_stubgen/_version.py
chaquopy_stubgen/chaquopy_bindings.py
chaquopy_stubgen/py.typed
chaquopy_stubgen/stubgen.py
chaquopy_stubgen-0.1.0.dist-info/licenses/LICENSE
chaquopy_stubgen-0.1.0.dist-info/METADATA
chaquopy_stubgen-0.1.0.dist-info/WHEEL
chaquopy_stubgen-0.1.0.dist-info/top_level.txt
chaquopy_stubgen-0.1.0.dist-info/RECORD
