Metadata-Version: 2.4
Name: chaquopy-stubgen
Version: 0.1.0
Summary: PEP484 python stub generator for Java classes accessed through Chaquopy on Android
License: MIT
Keywords: stubgen,JPype,Python,Java,Chaquopy,Beeware,briefcase,Android,PEP484
Classifier: Programming Language :: Python :: 3
Classifier: Operating System :: OS Independent
Requires-Python: >=3.13
License-File: LICENSE
Requires-Dist: JPype1<2,>=1.6.0
Dynamic: license-file
